ncbi_mesh_parser/__init__.py
ncbi_mesh_parser/desc_parser.py
ncbi_mesh_parser-1.0.0.dist-info/WHEEL
ncbi_mesh_parser-1.0.0.dist-info/METADATA
ncbi_mesh_parser-1.0.0.dist-info/RECORD
