Metadata-Version: 2.1
Name: ncbi-mesh-parser
Version: 1.0.0
Summary: Parse NCBI MeSH XML files
License: MIT
Author: Sean Davis
Author-email: seandavi@gmail.com
Requires-Python: >=3.9,<4.0
Classifier: License :: OSI Approved :: MIT License
Classifier: Programming Language :: Python :: 3
Classifier: Programming Language :: Python :: 3.10
Classifier: Programming Language :: Python :: 3.9
Requires-Dist: pydantic (>=1.10.2,<2.0.0)
